usgs_data_fetcher/__init__.py
usgs_data_fetcher/fetcher.py
usgs_data_fetcher/parameters.py
nwis_data_downloader-0.1.2.dist-info/METADATA
nwis_data_downloader-0.1.2.dist-info/WHEEL
nwis_data_downloader-0.1.2.dist-info/top_level.txt
nwis_data_downloader-0.1.2.dist-info/RECORD
