Metadata-Version: 2.4
Name: nwis-data-downloader
Version: 0.1.2
Summary: A Python package for downloading USGS NWIS hydrological data
Author: Shahab Shojaee
License: MIT
Project-URL: Homepage, https://github.com/Bluerrror/NWIS-Data-Downloader
Project-URL: Repository, https://github.com/Bluerrror/NWIS-Data-Downloader
Project-URL: Issues, https://github.com/Bluerrror/NWIS-Data-Downloader/issues
Keywords: hydrology,USGS,NWIS,water,data
Classifier: Programming Language :: Python :: 3
Classifier: License :: OSI Approved :: MIT License
Classifier: Operating System :: OS Independent
Requires-Python: >=3.8
Requires-Dist: requests
Requires-Dist: pandas
Dynamic: requires-python
